Metadata-Version: 1.0
Name: divinity
Version: 0.1
Summary: Auto Timeseries Forecast Package
Home-page: https://github.com/dstarkey23/divinity
Author: David Starkey
Author-email: davidstarkey29@gmail.com
License: Apache
Platform: UNKNOWN
